pycounts_ramg23/__init__.py
pycounts_ramg23/plotting.py
pycounts_ramg23/pycounts_ramg23.py
pycounts_ramg23-0.1.0.dist-info/LICENSE
pycounts_ramg23-0.1.0.dist-info/METADATA
pycounts_ramg23-0.1.0.dist-info/WHEEL
pycounts_ramg23-0.1.0.dist-info/RECORD
